{
    "project": "octopus-dev-309403",
    "region": "asia-east1",
    "cluster": "autopilot-cluster-1",
    "namespace": "testnet",

    "runes_oracle": {
        "image": "us-central1-docker.pkg.dev/octopus-prod/octopus/omnity@sha256:0bcf7ab8a85139e6c511c497b0bef9b39196f87d5629354b4830342ca6eaf691",
        "replicas": 1,
        "resources": {
            "cpu_requests": "250m",
            "cpu_limits": "250m",
            "memory_requests": "512Mi",
            "memory_limits": "512Mi"
        }
    },
    "INDEXER_URL": "http://localhost:23456",
    "IC_GATEWAY": "https://ic0.app",
    "CUSTOMS_CANISTER_ID": "x7lb2-jqaaa-aaaag-qjrkq-cai",
    "HUB_CANISTER_ID": "x7lb2-jqaaa-aaaag-qjrkq-cai"
}